[
  {
    "id": "TO-533411",
    "family": "夫婦",
    "age": "50歳",
    "occupation": "接客・サービス業",
    "timing": "6ヶ月以内",
    "method": "現金購入",
    "reason": "庭付きの家を建てたい",
    "ng": "特になし",
    "purpose": "駐車場用地",
    "landArea": "301㎡以上",
    "walkingDistance": "駅徒歩21分以上"
  },
  {
    "id": "TO-533412",
    "family": "夫婦+子供3人",
    "age": "50歳",
    "occupation": "マスコミ・広告業",
    "timing": "6ヶ月以内",
    "method": "住宅ローン",
    "reason": "注文住宅を建てたい",
    "ng": "水害リスクエリア",
    "purpose": "戸建住宅",
    "landArea": "151〜300㎡",
    "walkingDistance": "駅徒歩10分以内"
  },
  {
    "id": "TO-533413",
    "family": "夫婦+子供2人",
    "age": "42歳",
    "occupation": "警備員",
    "timing": "良い物件があれば",
    "method": "住宅ローン",
    "reason": "注文住宅を建てたい",
    "ng": "特になし",
    "purpose": "二世帯住宅",
    "landArea": "151〜300㎡",
    "walkingDistance": "駅徒歩11〜15分"
  },
  {
    "id": "TO-533414",
    "family": "夫婦+子供2人",
    "age": "39歳",
    "occupation": "ITエンジニア",
    "timing": "良い物件があれば",
    "method": "現金購入",
    "reason": "新築戸建を建てたい",
    "ng": "水害リスクエリア",
    "purpose": "二世帯住宅",
    "landArea": "301㎡以上",
    "walkingDistance": "駅徒歩10分以内"
  },
  {
    "id": "TO-533415",
    "family": "夫婦+子供2人",
    "age": "40歳",
    "occupation": "理美容・エステ関連",
    "timing": "1年以内",
    "method": "住宅ローン",
    "reason": "将来的な転売",
    "ng": "隣地との境界未確定",
    "purpose": "戸建住宅",
    "landArea": "特に希望なし",
    "walkingDistance": "駅徒歩11〜15分"
  },
  {
    "id": "TO-533416",
    "family": "夫婦+子供1人",
    "age": "48歳",
    "occupation": "飲食業",
    "timing": "1年以内",
    "method": "現金購入",
    "reason": "庭付きの家を建てたい",
    "ng": "傾斜地",
    "purpose": "戸建住宅",
    "landArea": "151〜300㎡",
    "walkingDistance": "駅徒歩11〜15分"
  },
  {
    "id": "TO-533417",
    "family": "単身",
    "age": "30歳",
    "occupation": "データ分析・AI関連職",
    "timing": "3ヶ月以内",
    "method": "親族の援助あり",
    "reason": "新築戸建を建てたい",
    "ng": "特になし",
    "purpose": "戸建住宅",
    "landArea": "51〜150㎡",
    "walkingDistance": "駅徒歩10分以内"
  },
  {
    "id": "TO-533418",
    "family": "夫婦+子供3人",
    "age": "35歳",
    "occupation": "ITエンジニア",
    "timing": "6ヶ月以内",
    "method": "住宅ローン",
    "reason": "注文住宅を建てたい",
    "ng": "特になし",
    "purpose": "戸建住宅",
    "landArea": "151〜300㎡",
    "walkingDistance": "駅徒歩11〜15分"
  },
  {
    "id": "TO-533419",
    "family": "夫婦+子供1人",
    "age": "44歳",
    "occupation": "医師",
    "timing": "良い物件があれば",
    "method": "買い替え",
    "reason": "子供の学区",
    "ng": "再建築不可",
    "purpose": "戸建住宅",
    "landArea": "51〜150㎡",
    "walkingDistance": "駅徒歩21分以上"
  },
  {
    "id": "TO-533420",
    "family": "夫婦+子供3人",
    "age": "33歳",
    "occupation": "公務員（国家公務員）",
    "timing": "即時",
    "method": "買い替え",
    "reason": "将来的な転売",
    "ng": "再建築不可",
    "purpose": "戸建住宅",
    "landArea": "特に希望なし",
    "walkingDistance": "駅徒歩11〜15分"
  },
  {
    "id": "TO-533421",
    "family": "夫婦+子供1人",
    "age": "40歳",
    "occupation": "マスコミ・広告業",
    "timing": "6ヶ月以内",
    "method": "住宅ローン",
    "reason": "ペットを飼いたい",
    "ng": "特になし",
    "purpose": "戸建住宅",
    "landArea": "151〜300㎡",
    "walkingDistance": "特に希望なし"
  },
  {
    "id": "TO-533422",
    "family": "単身",
    "age": "32歳",
    "occupation": "薬剤師",
    "timing": "3ヶ月以内",
    "method": "買い替え",
    "reason": "注文住宅を建てたい",
    "ng": "市街化調整区域",
    "purpose": "戸建住宅",
    "landArea": "151〜300㎡",
    "walkingDistance": "駅徒歩21分以上"
  },
  {
    "id": "TO-533423",
    "family": "夫婦+子供2人",
    "age": "38歳",
    "occupation": "介護士",
    "timing": "3ヶ月以内",
    "method": "現金購入",
    "reason": "新築戸建を建てたい",
    "ng": "特になし",
    "purpose": "戸建住宅",
    "landArea": "301㎡以上",
    "walkingDistance": "駅徒歩10分以内"
  },
  {
    "id": "TO-533424",
    "family": "単身",
    "age": "42歳",
    "occupation": "理美容・エステ関連",
    "timing": "1年以内",
    "method": "親族の援助あり",
    "reason": "駐車場が必要",
    "ng": "特になし",
    "purpose": "戸建住宅",
    "landArea": "151〜300㎡",
    "walkingDistance": "駅徒歩21分以上"
  },
  {
    "id": "TO-533425",
    "family": "夫婦+子供2人",
    "age": "45歳",
    "occupation": "歯科医師",
    "timing": "6ヶ月以内",
    "method": "住宅ローン",
    "reason": "新築戸建を建てたい",
    "ng": "再建築不可",
    "purpose": "二世帯住宅",
    "landArea": "301㎡以上",
    "walkingDistance": "駅徒歩10分以内"
  },
  {
    "id": "TO-533426",
    "family": "夫婦+子供2人",
    "age": "38歳",
    "occupation": "理学療法士・作業療法士",
    "timing": "6ヶ月以内",
    "method": "親族の援助あり",
    "reason": "注文住宅を建てたい",
    "ng": "特になし",
    "purpose": "戸建住宅",
    "landArea": "151〜300㎡",
    "walkingDistance": "駅徒歩16〜20分"
  },
  {
    "id": "TO-533427",
    "family": "夫婦",
    "age": "48歳",
    "occupation": "経営者・役員",
    "timing": "1年以内",
    "method": "住宅ローン",
    "reason": "資産形成",
    "ng": "再建築不可",
    "purpose": "二世帯住宅",
    "landArea": "151〜300㎡",
    "walkingDistance": "駅徒歩10分以内"
  },
  {
    "id": "TO-533428",
    "family": "夫婦",
    "age": "40歳",
    "occupation": "警備員",
    "timing": "1年以内",
    "method": "現金購入",
    "reason": "広い家を建てたい",
    "ng": "傾斜地",
    "purpose": "戸建住宅",
    "landArea": "特に希望なし",
    "walkingDistance": "駅徒歩10分以内"
  },
  {
    "id": "TO-533429",
    "family": "夫婦+子供1人",
    "age": "36歳",
    "occupation": "技術職（エンジニア）",
    "timing": "3ヶ月以内",
    "method": "買い替え",
    "reason": "新築戸建を建てたい",
    "ng": "特になし",
    "purpose": "賃貸併用住宅",
    "landArea": "301㎡以上",
    "walkingDistance": "駅徒歩11〜15分"
  },
  {
    "id": "TO-533430",
    "family": "夫婦+子供1人",
    "age": "45歳",
    "occupation": "販売職（小売）",
    "timing": "3ヶ月以内",
    "method": "親族の援助あり",
    "reason": "資産形成",
    "ng": "水害リスクエリア",
    "purpose": "賃貸併用住宅",
    "landArea": "301㎡以上",
    "walkingDistance": "駅徒歩16〜20分"
  },
  {
    "id": "TO-533431",
    "family": "夫婦+子供2人",
    "age": "44歳",
    "occupation": "研究職",
    "timing": "6ヶ月以内",
    "method": "買い替え",
    "reason": "注文住宅を建てたい",
    "ng": "特になし",
    "purpose": "戸建住宅",
    "landArea": "51〜150㎡",
    "walkingDistance": "特に希望なし"
  },
  {
    "id": "TO-533432",
    "family": "夫婦",
    "age": "39歳",
    "occupation": "運送・物流業",
    "timing": "6ヶ月以内",
    "method": "現金購入",
    "reason": "庭付きの家を建てたい",
    "ng": "特になし",
    "purpose": "戸建住宅",
    "landArea": "301㎡以上",
    "walkingDistance": "駅徒歩16〜20分"
  },
  {
    "id": "TO-533433",
    "family": "夫婦+子供2人",
    "age": "32歳",
    "occupation": "不動産業",
    "timing": "1年以内",
    "method": "現金購入",
    "reason": "庭付きの家を建てたい",
    "ng": "再建築不可",
    "purpose": "賃貸併用住宅",
    "landArea": "301㎡以上",
    "walkingDistance": "駅徒歩11〜15分"
  },
  {
    "id": "TO-533434",
    "family": "夫婦+子供1人",
    "age": "43歳",
    "occupation": "研究職",
    "timing": "3ヶ月以内",
    "method": "住宅ローン",
    "reason": "静かな環境",
    "ng": "特になし",
    "purpose": "戸建住宅",
    "landArea": "151〜300㎡",
    "walkingDistance": "駅徒歩10分以内"
  },
  {
    "id": "TO-533435",
    "family": "夫婦+子供2人",
    "age": "42歳",
    "occupation": "医師",
    "timing": "1年以内",
    "method": "親族の援助あり",
    "reason": "子供の学区",
    "ng": "特になし",
    "purpose": "賃貸併用住宅",
    "landArea": "特に希望なし",
    "walkingDistance": "特に希望なし"
  },
  {
    "id": "TO-533436",
    "family": "夫婦+子供1人",
    "age": "38歳",
    "occupation": "会社員（一般職）",
    "timing": "3ヶ月以内",
    "method": "住宅ローン",
    "reason": "子供の学区",
    "ng": "特になし",
    "purpose": "二世帯住宅",
    "landArea": "151〜300㎡",
    "walkingDistance": "駅徒歩21分以上"
  },
  {
    "id": "TO-533437",
    "family": "夫婦+子供1人",
    "age": "45歳",
    "occupation": "公務員（国家公務員）",
    "timing": "6ヶ月以内",
    "method": "親族の援助あり",
    "reason": "駐車場が必要",
    "ng": "接道不良",
    "purpose": "戸建住宅",
    "landArea": "151〜300㎡",
    "walkingDistance": "駅徒歩11〜15分"
  },
  {
    "id": "TO-533438",
    "family": "夫婦+子供3人",
    "age": "42歳",
    "occupation": "教員（大学・専門学校）",
    "timing": "1年以内",
    "method": "住宅ローン",
    "reason": "二世帯住宅を建てたい",
    "ng": "地盤が弱い",
    "purpose": "戸建住宅",
    "landArea": "301㎡以上",
    "walkingDistance": "駅徒歩16〜20分"
  },
  {
    "id": "TO-533439",
    "family": "三世代同居希望",
    "age": "40歳",
    "occupation": "警備員",
    "timing": "即時",
    "method": "住宅ローン",
    "reason": "注文住宅を建てたい",
    "ng": "特になし",
    "purpose": "戸建住宅",
    "landArea": "151〜300㎡",
    "walkingDistance": "特に希望なし"
  },
  {
    "id": "TO-533440",
    "family": "夫婦+子供1人",
    "age": "39歳",
    "occupation": "カメラマン",
    "timing": "良い物件があれば",
    "method": "親族の援助あり",
    "reason": "新築戸建を建てたい",
    "ng": "特になし",
    "purpose": "戸建住宅",
    "landArea": "特に希望なし",
    "walkingDistance": "駅徒歩16〜20分"
  }
]