[
  {
    "id": "TO-32606",
    "family": "夫婦+子供1人",
    "age": "33歳",
    "occupation": "ITエンジニア",
    "timing": "即時",
    "method": "住宅ローン",
    "reason": "新築戸建を建てたい",
    "ng": "隣地との境界未確定",
    "purpose": "戸建住宅",
    "landArea": "151〜300㎡",
    "walkingDistance": "駅徒歩21分以上"
  },
  {
    "id": "TO-32607",
    "family": "夫婦+子供1人",
    "age": "42歳",
    "occupation": "歯科医師",
    "timing": "3ヶ月以内",
    "method": "親族の援助あり",
    "reason": "新築戸建を建てたい",
    "ng": "隣地との境界未確定",
    "purpose": "戸建住宅",
    "landArea": "〜50㎡",
    "walkingDistance": "駅徒歩10分以内"
  },
  {
    "id": "TO-32608",
    "family": "親との同居予定",
    "age": "45歳",
    "occupation": "販売職（小売）",
    "timing": "6ヶ月以内",
    "method": "住宅ローン",
    "reason": "資産形成",
    "ng": "市街化調整区域",
    "purpose": "戸建住宅",
    "landArea": "301㎡以上",
    "walkingDistance": "駅徒歩21分以上"
  },
  {
    "id": "TO-32609",
    "family": "夫婦",
    "age": "35歳",
    "occupation": "公務員（国家公務員）",
    "timing": "良い物件があれば",
    "method": "親族の援助あり",
    "reason": "資産形成",
    "ng": "特になし",
    "purpose": "駐車場用地",
    "landArea": "51〜150㎡",
    "walkingDistance": "駅徒歩11〜15分"
  },
  {
    "id": "TO-32610",
    "family": "夫婦+子供1人",
    "age": "50歳",
    "occupation": "建設業",
    "timing": "即時",
    "method": "現金購入",
    "reason": "注文住宅を建てたい",
    "ng": "特になし",
    "purpose": "賃貸併用住宅",
    "landArea": "151〜300㎡",
    "walkingDistance": "駅徒歩21分以上"
  },
  {
    "id": "TO-32611",
    "family": "親との同居予定",
    "age": "52歳",
    "occupation": "会社員（一般職）",
    "timing": "3ヶ月以内",
    "method": "住宅ローン",
    "reason": "注文住宅を建てたい",
    "ng": "隣地との境界未確定",
    "purpose": "戸建住宅",
    "landArea": "51〜150㎡",
    "walkingDistance": "駅徒歩11〜15分"
  },
  {
    "id": "TO-32612",
    "family": "夫婦+子供2人",
    "age": "49歳",
    "occupation": "薬剤師",
    "timing": "良い物件があれば",
    "method": "住宅ローン",
    "reason": "注文住宅を建てたい",
    "ng": "墓地や葬儀場の近く",
    "purpose": "二世帯住宅",
    "landArea": "151〜300㎡",
    "walkingDistance": "駅徒歩10分以内"
  },
  {
    "id": "TO-32613",
    "family": "夫婦+子供2人",
    "age": "35歳",
    "occupation": "システムエンジニア（SE）",
    "timing": "6ヶ月以内",
    "method": "買い替え",
    "reason": "注文住宅を建てたい",
    "ng": "傾斜地",
    "purpose": "戸建住宅",
    "landArea": "301㎡以上",
    "walkingDistance": "駅徒歩11〜15分"
  },
  {
    "id": "TO-32614",
    "family": "親との同居予定",
    "age": "45歳",
    "occupation": "公務員（国家公務員）",
    "timing": "良い物件があれば",
    "method": "現金購入",
    "reason": "二世帯住宅を建てたい",
    "ng": "傾斜地",
    "purpose": "二世帯住宅",
    "landArea": "151〜300㎡",
    "walkingDistance": "駅徒歩10分以内"
  },
  {
    "id": "TO-32615",
    "family": "親との同居予定",
    "age": "58歳",
    "occupation": "製造業",
    "timing": "即時",
    "method": "住宅ローン",
    "reason": "二世帯住宅を建てたい",
    "ng": "特になし",
    "purpose": "戸建住宅",
    "landArea": "51〜150㎡",
    "walkingDistance": "駅徒歩16〜20分"
  },
  {
    "id": "TO-32616",
    "family": "夫婦+子供1人",
    "age": "40歳",
    "occupation": "医師",
    "timing": "3ヶ月以内",
    "method": "住宅ローン",
    "reason": "注文住宅を建てたい",
    "ng": "隣地との境界未確定",
    "purpose": "戸建住宅",
    "landArea": "151〜300㎡",
    "walkingDistance": "駅徒歩11〜15分"
  },
  {
    "id": "TO-32617",
    "family": "夫婦",
    "age": "54歳",
    "occupation": "製造業",
    "timing": "6ヶ月以内",
    "method": "現金購入",
    "reason": "投資用地として",
    "ng": "墓地や葬儀場の近く",
    "purpose": "投資用地",
    "landArea": "151〜300㎡",
    "walkingDistance": "駅徒歩21分以上"
  },
  {
    "id": "TO-32618",
    "family": "夫婦",
    "age": "44歳",
    "occupation": "技術職（エンジニア）",
    "timing": "良い物件があれば",
    "method": "現金購入",
    "reason": "静かな環境",
    "ng": "水害リスクエリア",
    "purpose": "戸建住宅",
    "landArea": "151〜300㎡",
    "walkingDistance": "駅徒歩11〜15分"
  },
  {
    "id": "TO-32619",
    "family": "夫婦+子供1人",
    "age": "44歳",
    "occupation": "会社員（一般職）",
    "timing": "良い物件があれば",
    "method": "現金購入",
    "reason": "注文住宅を建てたい",
    "ng": "隣地との境界未確定",
    "purpose": "戸建住宅",
    "landArea": "151〜300㎡",
    "walkingDistance": "駅徒歩16〜20分"
  },
  {
    "id": "TO-32620",
    "family": "夫婦+子供2人",
    "age": "47歳",
    "occupation": "技術職（エンジニア）",
    "timing": "即時",
    "method": "住宅ローン",
    "reason": "二世帯住宅を建てたい",
    "ng": "市街化調整区域",
    "purpose": "二世帯住宅",
    "landArea": "151〜300㎡",
    "walkingDistance": "駅徒歩10分以内"
  },
  {
    "id": "TO-32621",
    "family": "夫婦+子供1人",
    "age": "43歳",
    "occupation": "製造業",
    "timing": "3ヶ月以内",
    "method": "親族の援助あり",
    "reason": "注文住宅を建てたい",
    "ng": "隣地との境界未確定",
    "purpose": "戸建住宅",
    "landArea": "301㎡以上",
    "walkingDistance": "駅徒歩11〜15分"
  },
  {
    "id": "TO-32622",
    "family": "夫婦+子供2人",
    "age": "42歳",
    "occupation": "薬剤師",
    "timing": "6ヶ月以内",
    "method": "現金購入",
    "reason": "二世帯住宅を建てたい",
    "ng": "特になし",
    "purpose": "二世帯住宅",
    "landArea": "301㎡以上",
    "walkingDistance": "駅徒歩21分以上"
  },
  {
    "id": "TO-32623",
    "family": "夫婦+子供2人",
    "age": "37歳",
    "occupation": "教員（小・中・高校）",
    "timing": "良い物件があれば",
    "method": "親族の援助あり",
    "reason": "二世帯住宅を建てたい",
    "ng": "特になし",
    "purpose": "二世帯住宅",
    "landArea": "301㎡以上",
    "walkingDistance": "駅徒歩21分以上"
  },
  {
    "id": "TO-32624",
    "family": "単身",
    "age": "45歳",
    "occupation": "歯科医師",
    "timing": "良い物件があれば",
    "method": "住宅ローン",
    "reason": "新築戸建を建てたい",
    "ng": "特になし",
    "purpose": "戸建住宅",
    "landArea": "151〜300㎡",
    "walkingDistance": "駅徒歩21分以上"
  },
  {
    "id": "TO-32625",
    "family": "三世代同居希望",
    "age": "55歳",
    "occupation": "歯科医師",
    "timing": "即時",
    "method": "現金購入",
    "reason": "実家の近く",
    "ng": "隣地との境界未確定",
    "purpose": "戸建住宅",
    "landArea": "301㎡以上",
    "walkingDistance": "駅徒歩21分以上"
  },
  {
    "id": "TO-32626",
    "family": "夫婦+子供1人",
    "age": "39歳",
    "occupation": "歯科医師",
    "timing": "3ヶ月以内",
    "method": "住宅ローン",
    "reason": "子供の学区",
    "ng": "特になし",
    "purpose": "戸建住宅",
    "landArea": "301㎡以上",
    "walkingDistance": "駅徒歩10分以内"
  },
  {
    "id": "TO-32627",
    "family": "夫婦+子供1人",
    "age": "48歳",
    "occupation": "教員（小・中・高校）",
    "timing": "6ヶ月以内",
    "method": "住宅ローン",
    "reason": "事業用地として",
    "ng": "特になし",
    "purpose": "戸建住宅",
    "landArea": "151〜300㎡",
    "walkingDistance": "駅徒歩11〜15分"
  },
  {
    "id": "TO-32628",
    "family": "夫婦+子供2人",
    "age": "38歳",
    "occupation": "教員（小・中・高校）",
    "timing": "良い物件があれば",
    "method": "住宅ローン",
    "reason": "広い家を建てたい",
    "ng": "接道不良",
    "purpose": "戸建住宅",
    "landArea": "151〜300㎡",
    "walkingDistance": "駅徒歩21分以上"
  },
  {
    "id": "TO-32629",
    "family": "夫婦+子供1人",
    "age": "45歳",
    "occupation": "清掃業",
    "timing": "即時",
    "method": "住宅ローン",
    "reason": "注文住宅を建てたい",
    "ng": "特になし",
    "purpose": "賃貸併用住宅",
    "landArea": "151〜300㎡",
    "walkingDistance": "駅徒歩10分以内"
  },
  {
    "id": "TO-32630",
    "family": "夫婦+子供1人",
    "age": "39歳",
    "occupation": "個人事業主",
    "timing": "3ヶ月以内",
    "method": "現金購入",
    "reason": "事業用地として",
    "ng": "地盤が弱い",
    "purpose": "事業用地",
    "landArea": "301㎡以上",
    "walkingDistance": "駅徒歩10分以内"
  },
  {
    "id": "TO-32631",
    "family": "親との同居予定",
    "age": "53歳",
    "occupation": "公務員（国家公務員）",
    "timing": "良い物件があれば",
    "method": "住宅ローン",
    "reason": "二世帯住宅を建てたい",
    "ng": "特になし",
    "purpose": "二世帯住宅",
    "landArea": "301㎡以上",
    "walkingDistance": "駅徒歩10分以内"
  },
  {
    "id": "TO-32632",
    "family": "夫婦+子供1人",
    "age": "47歳",
    "occupation": "看護師",
    "timing": "6ヶ月以内",
    "method": "親族の援助あり",
    "reason": "子供の学区",
    "ng": "隣地との境界未確定",
    "purpose": "戸建住宅",
    "landArea": "151〜300㎡",
    "walkingDistance": "駅徒歩21分以上"
  },
  {
    "id": "TO-32633",
    "family": "夫婦+子供2人",
    "age": "47歳",
    "occupation": "建設業",
    "timing": "良い物件があれば",
    "method": "現金購入",
    "reason": "新築戸建を建てたい",
    "ng": "接道不良",
    "purpose": "戸建住宅",
    "landArea": "151〜300㎡",
    "walkingDistance": "駅徒歩16〜20分"
  },
  {
    "id": "TO-32634",
    "family": "親との同居予定",
    "age": "53歳",
    "occupation": "歯科医師",
    "timing": "即時",
    "method": "住宅ローン",
    "reason": "二世帯住宅を建てたい",
    "ng": "再建築不可",
    "purpose": "二世帯住宅",
    "landArea": "151〜300㎡",
    "walkingDistance": "駅徒歩10分以内"
  },
  {
    "id": "TO-32635",
    "family": "夫婦+子供3人",
    "age": "47歳",
    "occupation": "ITエンジニア",
    "timing": "3ヶ月以内",
    "method": "親族の援助あり",
    "reason": "資産形成",
    "ng": "接道不良",
    "purpose": "駐車場用地",
    "landArea": "51〜150㎡",
    "walkingDistance": "駅徒歩16〜20分"
  },
  {
    "id": "TO-32636",
    "family": "単身",
    "age": "43歳",
    "occupation": "薬剤師",
    "timing": "6ヶ月以内",
    "method": "親族の援助あり",
    "reason": "新築戸建を建てたい",
    "ng": "傾斜地",
    "purpose": "賃貸併用住宅",
    "landArea": "151〜300㎡",
    "walkingDistance": "駅徒歩11〜15分"
  },
  {
    "id": "TO-32637",
    "family": "夫婦+子供3人",
    "age": "47歳",
    "occupation": "経営者・役員",
    "timing": "良い物件があれば",
    "method": "現金購入",
    "reason": "注文住宅を建てたい",
    "ng": "特になし",
    "purpose": "戸建住宅",
    "landArea": "301㎡以上",
    "walkingDistance": "駅徒歩11〜15分"
  },
  {
    "id": "TO-32638",
    "family": "夫婦+子供2人",
    "age": "39歳",
    "occupation": "製造業",
    "timing": "良い物件があれば",
    "method": "現金購入",
    "reason": "ペットを飼いたい",
    "ng": "傾斜地",
    "purpose": "戸建住宅",
    "landArea": "301㎡以上",
    "walkingDistance": "駅徒歩21分以上"
  },
  {
    "id": "TO-32639",
    "family": "三世代同居希望",
    "age": "35歳",
    "occupation": "カメラマン",
    "timing": "即時",
    "method": "住宅ローン",
    "reason": "新築戸建を建てたい",
    "ng": "市街化調整区域",
    "purpose": "戸建住宅",
    "landArea": "151〜300㎡",
    "walkingDistance": "駅徒歩11〜15分"
  },
  {
    "id": "TO-32640",
    "family": "夫婦+子供1人",
    "age": "47歳",
    "occupation": "薬剤師",
    "timing": "3ヶ月以内",
    "method": "現金購入",
    "reason": "新築戸建を建てたい",
    "ng": "不整形地",
    "purpose": "戸建住宅",
    "landArea": "51〜150㎡",
    "walkingDistance": "駅徒歩10分以内"
  },
  {
    "id": "TO-32641",
    "family": "単身",
    "age": "44歳",
    "occupation": "プログラマー",
    "timing": "6ヶ月以内",
    "method": "現金購入",
    "reason": "事業用地として",
    "ng": "再建築不可",
    "purpose": "事業用地",
    "landArea": "301㎡以上",
    "walkingDistance": "駅徒歩10分以内"
  },
  {
    "id": "TO-32642",
    "family": "夫婦+子供2人",
    "age": "48歳",
    "occupation": "教員（大学・専門学校）",
    "timing": "良い物件があれば",
    "method": "住宅ローン",
    "reason": "資産形成",
    "ng": "水害リスクエリア",
    "purpose": "戸建住宅",
    "landArea": "51〜150㎡",
    "walkingDistance": "駅徒歩21分以上"
  },
  {
    "id": "TO-32643",
    "family": "夫婦+子供1人",
    "age": "37歳",
    "occupation": "教員（小・中・高校）",
    "timing": "良い物件があれば",
    "method": "住宅ローン",
    "reason": "資産形成",
    "ng": "特になし",
    "purpose": "戸建住宅",
    "landArea": "301㎡以上",
    "walkingDistance": "駅徒歩21分以上"
  },
  {
    "id": "TO-32644",
    "family": "夫婦+子供2人",
    "age": "45歳",
    "occupation": "理学療法士・作業療法士",
    "timing": "即時",
    "method": "住宅ローン",
    "reason": "実家の近く",
    "ng": "特になし",
    "purpose": "戸建住宅",
    "landArea": "151〜300㎡",
    "walkingDistance": "駅徒歩21分以上"
  },
  {
    "id": "TO-32645",
    "family": "夫婦+子供2人",
    "age": "37歳",
    "occupation": "公務員（地方公務員）",
    "timing": "3ヶ月以内",
    "method": "親族の援助あり",
    "reason": "注文住宅を建てたい",
    "ng": "特になし",
    "purpose": "戸建住宅",
    "landArea": "151〜300㎡",
    "walkingDistance": "駅徒歩11〜15分"
  },
  {
    "id": "TO-32646",
    "family": "夫婦+子供2人",
    "age": "47歳",
    "occupation": "建設業",
    "timing": "6ヶ月以内",
    "method": "親族の援助あり",
    "reason": "子供の学区",
    "ng": "特になし",
    "purpose": "戸建住宅",
    "landArea": "301㎡以上",
    "walkingDistance": "駅徒歩21分以上"
  },
  {
    "id": "TO-32647",
    "family": "夫婦+子供2人",
    "age": "41歳",
    "occupation": "ITエンジニア",
    "timing": "良い物件があれば",
    "method": "現金購入",
    "reason": "新築戸建を建てたい",
    "ng": "市街化調整区域",
    "purpose": "戸建住宅",
    "landArea": "151〜300㎡",
    "walkingDistance": "駅徒歩10分以内"
  }
]